[
    {
        "type": "message",
        "text": "Навальный <https:\/\/navalny.com\/p\/4585\/> со ссылкой на Волкова <http:\/\/www.leonidvolkov.ru\/p\/88\/> обсуждают “Активный гражданин”. В ленте выпало. \nПубличная преза отличалась от оригинальной (оригинал брать тут - <https:\/\/drive.google.com\/file\/d\/0B3e_k69gW3vzYmlLMm5NWFRJZ2M\/view>)",
        "user": "U0AJU5AMA",
        "ts": "1449231711.000006",
        "team": "T040HKJE3",
        "user_team": "T040HKJE3",
        "source_team": "T040HKJE3",
        "user_profile": {
            "avatar_hash": "gbb21f67d330",
            "image_72": "https:\/\/secure.gravatar.com\/avatar\/f6bb21f67d330be3c32e584dfaa9d021.jpg?s=72&d=https%3A%2F%2Fa.slack-edge.com%2Fdf10d%2Fimg%2Favatars%2Fava_0013-72.png",
            "first_name": "Jin",
            "real_name": "Jin Kolesnikov",
            "display_name": "jinkolesnikov",
            "team": "T040HKJE3",
            "name": "jinkolesnikov",
            "is_restricted": false,
            "is_ultra_restricted": false
        },
        "attachments": [
            {
                "service_name": "Алексей Навальный",
                "title": "Чёрный Ящик об Активном гражданине",
                "title_link": "https:\/\/navalny.com\/p\/4585\/",
                "text": "Закрытая презентация мэрии об «Активном гражданине» (прислали нам на Чёрный Ящик) прекрасна в своей циничности. Почитайте Волкова, он подробно об этом пишет.",
                "fallback": "Алексей Навальный: Чёрный Ящик об Активном гражданине",
                "image_url": "https:\/\/navalny.com\/media\/cache\/6b\/38\/6b38801d36a45691b6c7c7cd763fda59.jpg",
                "from_url": "https:\/\/navalny.com\/p\/4585\/",
                "image_width": 466,
                "image_height": 250,
                "image_bytes": 143182,
                "id": 1
            },
            {
                "service_name": "Леонид Волков",
                "title": "Лояльный гражданин",
                "title_link": "http:\/\/www.leonidvolkov.ru\/p\/88\/",
                "text": "В Москве позавчера проходил «Московский гражданский форум», одной из ключевых его тем была электронная демократия, главной звездой — могущественный вице-мэр Анастасия Ракова. Презентационные материалы мэрии, на отличном уровне исполнения, свидетельствуют о том, как растет вовлеченность москвичей в п",
                "fallback": "Леонид Волков: Лояльный гражданин",
                "image_url": "http:\/\/www.leonidvolkov.ru\/media\/cache\/44\/8f\/448f52c8aada81f3afad0241f459a968.jpg",
                "from_url": "http:\/\/www.leonidvolkov.ru\/p\/88\/",
                "image_width": 656,
                "image_height": 250,
                "image_bytes": 82277,
                "id": 2
            }
        ]
    },
    {
        "type": "message",
        "text": "Суть в том, что можно из этого попробовать кейс сделать, только не ясно кому продавать. У меня входов в большое правительство напрямую почти нет. Тут думать надо.\nОчевидная идея вместо фейковых десятков тысяч работать по соцсеточкам по выявлениям настроений. Вторая - влиять на них ботами.",
        "user": "U0AJU5AMA",
        "ts": "1449231827.000008",
        "team": "T040HKJE3",
        "user_team": "T040HKJE3",
        "source_team": "T040HKJE3",
        "user_profile": {
            "avatar_hash": "gbb21f67d330",
            "image_72": "https:\/\/secure.gravatar.com\/avatar\/f6bb21f67d330be3c32e584dfaa9d021.jpg?s=72&d=https%3A%2F%2Fa.slack-edge.com%2Fdf10d%2Fimg%2Favatars%2Fava_0013-72.png",
            "first_name": "Jin",
            "real_name": "Jin Kolesnikov",
            "display_name": "jinkolesnikov",
            "team": "T040HKJE3",
            "name": "jinkolesnikov",
            "is_restricted": false,
            "is_ultra_restricted": false
        }
    },
    {
        "type": "message",
        "text": "Что думаете?",
        "user": "U0AJU5AMA",
        "ts": "1449231836.000009",
        "team": "T040HKJE3",
        "user_team": "T040HKJE3",
        "source_team": "T040HKJE3",
        "user_profile": {
            "avatar_hash": "gbb21f67d330",
            "image_72": "https:\/\/secure.gravatar.com\/avatar\/f6bb21f67d330be3c32e584dfaa9d021.jpg?s=72&d=https%3A%2F%2Fa.slack-edge.com%2Fdf10d%2Fimg%2Favatars%2Fava_0013-72.png",
            "first_name": "Jin",
            "real_name": "Jin Kolesnikov",
            "display_name": "jinkolesnikov",
            "team": "T040HKJE3",
            "name": "jinkolesnikov",
            "is_restricted": false,
            "is_ultra_restricted": false
        }
    },
    {
        "type": "message",
        "subtype": "channel_join",
        "ts": "1449296199.000010",
        "user": "U045BH6SM",
        "text": "<@U045BH6SM> has joined the channel"
    }
]