[
    {
        "type": "message",
        "subtype": "channel_join",
        "ts": "1501165470.720376",
        "user": "U47EZESD8",
        "text": "<@U47EZESD8> has joined the channel"
    },
    {
        "type": "message",
        "text": "<https:\/\/opendatascience.slack.com\/archives\/C040HKJEZ\/p1501164191067651>",
        "user": "U47EZESD8",
        "ts": "1501165475.723406",
        "team": "T040HKJE3",
        "user_team": "T040HKJE3",
        "source_team": "T040HKJE3",
        "user_profile": {
            "avatar_hash": "32f8ee79d56e",
            "image_72": "https:\/\/avatars.slack-edge.com\/2017-03-16\/154456742608_32f8ee79d56e4ff029df_72.jpg",
            "first_name": "Nickolai",
            "real_name": "Nickolai Kruglikov",
            "display_name": "untech",
            "team": "T040HKJE3",
            "name": "untech",
            "is_restricted": false,
            "is_ultra_restricted": false
        },
        "attachments": [
            {
                "from_url": "https:\/\/opendatascience.slack.com\/archives\/C040HKJEZ\/p1501164191067651",
                "fallback": "[July 27th, 2017 7:03 AM] natekin: *Hi, <!everyone>!*\n\nУ нас накопился ряд новостей, а также активностей, на которые мы ищем вашей помощи!\n\n*0.* Мы завели англоязычный twitter-аккаунт, где мы будем делиться с миром нашими новостями: <https:\/\/twitter.com\/odsai_en\/> \n\n*1.* Сейчас идёт Turing.DeepHack <#C074F6E1K|deephack> - команды соревнуются в предсказании оценок людей при общении с ботами. Самое важное для любой модели - это данные, много данных. Если у вас есть желание помочь участникам хакатона и, больше того, современной науке, то от вас нужно только иметь (или быть готовым завести) аккаунт в Telegram, знать английский язык на уровне дружеской переписки и добавить бота @ConvaiBot . Подробная инструкция тут: <https:\/\/goo.gl\/w9TUWQ>  \n\n*2.* К сожалению, нам пришлось перенести <#C0E2T8WNM|data_fest> с 2-3 сентября. Мы не успевали все подготовить достаточно круто, поэтому решили перенести Московский фест на несколько месяцев. \nТем не менее, на 1-3 сентября у нас все-равно пройдет ряд митапов в Москве, начиная с Moscow Data Science Meetup в пятницу 1го сентября. Также у нас уже запланирована плотная сетка самых разных митапов, хакатонов и других мероприятий на осень. И конечно же, <#C0E2T8WNM|data_fest> пройдет еще в паре городов, о чем мы с вами поделимся, как только будут утверждены даты!\n\n*3.* Новый запуск открытого курса ODS по машинному обучению уже 6 сентября! Статьи останутся те же (вот первая <https:\/\/habrahabr.ru\/company\/ods\/blog\/322626\/> ), но вас ожидают новые домашние задания, тьюториалы, соревнования, а главное – индивидуальные проекты по анализу данных. Более того, в этот раз наши преподаватели <@U1UNFRQ1K>, <@U044084RH> и <@U040HKJE7> будут проводить лекции по материалам курса, площадкой выступит <http:\/\/Mail.ru|Mail.ru>. Готовьтесь, скоро будет и официальный анонс.\n\n*4.* ОDS растет и развивается не только в Москве - есть и локальные тусовки!\n- В Минске прошла первая тренировка (и планируется следующая), в эту субботу пройдет первый Дата Завтрак, а в августе состоится митап под эгидой ODS. Вся движуха в <#C4TJ1PLKV|_meetings_minsk>.\n- В Киеве и Львове регулярно проходят встречи Ukrainian Data Science Club по вторникам и субботам. Часть людей занимается time series, часть CV – мультиклассовая классификация, knowledge distillation и оптимизация сеточек. Больше информации в <#C0VL96SJ2|_meetings_ukraine> и тут: <https:\/\/www.facebook.com\/groups\/1081438678569043\/>\n- Продолжаются тренировки в Одессе. Ближайшая состоится вечером в среду 9 августа в ОНУ им. Мечникова. Подробности в <#C0VL96SJ2|_meetings_ukraine>.\n- Мероприятия активно проходят и в других городах России. Например, в следующую среду в Новосибирске пройдет митап в 2ГИС <#C0KUUAAJZ|_meetings_siberia>. А ближе к осени тренировки и DS митапы вновь запустятся по всему СНГ.\n- Возвращаясь к тренировкам <#C1CEM43TJ|mltrainings_live> - ближайшая встреча в Москве пройдет уже в эту субботу 29 июля: <https:\/\/events.yandex.ru\/events\/mltr\/29-jul-2017\/>\n\n*5.* Осенью мы планируем запустить новый сезон сериала про машинное обучение на хабре. Хотелось бы в течение осени публиковать как минимум по одной статье в неделю в блоге на хабре <https:\/\/habrahabr.ru\/company\/ods\/>. \nСейчас на нас подписано 1600 человек, и эта цифра растет ежедневно. В среднем в сутки наши статьи набирают по 5000 просмотров, а в дни публикаций и до 10 000. За весенний сезон мы смогли подняться на третье место в рейтинге компаний (и за лето упасть до 15-20). В новом сезоне хотелось бы добиться еще лучших результатов, но без вас, естественно, мы не справимся. \nЕсли вы очень хотите написать пост про ваш опыт, про какую-либо статью, которую вы недавно прочитали, про какую-то базовую модель, да вообще про что угодно – пишите <@U06J1LG1M>. У нас есть табличка куда можно вписать свое имя и тему поста <https:\/\/goo.gl\/2KHD9B>, дату публикации можно вводить с погрешностью 1-2 недели.\n\n*P.S.* Сухая статистика: 5413 участников, 1.25М сообщений от участников (новая аналитика не включает сообщения от ботов, и такие технические вещи как добавленные файлы)",
                "ts": "1501164191.067651",
                "author_subname": "natekin",
                "channel_id": "C040HKJEZ",
                "channel_name": "_general",
                "is_msg_unfurl": true,
                "text": "*Hi, <!everyone>!*\n\nУ нас накопился ряд новостей, а также активностей, на которые мы ищем вашей помощи!\n\n*0.* Мы завели англоязычный twitter-аккаунт, где мы будем делиться с миром нашими новостями: <https:\/\/twitter.com\/odsai_en\/> \n\n*1.* Сейчас идёт Turing.DeepHack <#C074F6E1K|deephack> - команды соревнуются в предсказании оценок людей при общении с ботами. Самое важное для любой модели - это данные, много данных. Если у вас есть желание помочь участникам хакатона и, больше того, современной науке, то от вас нужно только иметь (или быть готовым завести) аккаунт в Telegram, знать английский язык на уровне дружеской переписки и добавить бота @ConvaiBot . Подробная инструкция тут: <https:\/\/goo.gl\/w9TUWQ>  \n\n*2.* К сожалению, нам пришлось перенести <#C0E2T8WNM|data_fest> с 2-3 сентября. Мы не успевали все подготовить достаточно круто, поэтому решили перенести Московский фест на несколько месяцев. \nТем не менее, на 1-3 сентября у нас все-равно пройдет ряд митапов в Москве, начиная с Moscow Data Science Meetup в пятницу 1го сентября. Также у нас уже запланирована плотная сетка самых разных митапов, хакатонов и других мероприятий на осень. И конечно же, <#C0E2T8WNM|data_fest> пройдет еще в паре городов, о чем мы с вами поделимся, как только будут утверждены даты!\n\n*3.* Новый запуск открытого курса ODS по машинному обучению уже 6 сентября! Статьи останутся те же (вот первая <https:\/\/habrahabr.ru\/company\/ods\/blog\/322626\/> ), но вас ожидают новые домашние задания, тьюториалы, соревнования, а главное – индивидуальные проекты по анализу данных. Более того, в этот раз наши преподаватели <@U1UNFRQ1K>, <@U044084RH> и <@U040HKJE7> будут проводить лекции по материалам курса, площадкой выступит <http:\/\/Mail.ru|Mail.ru>. Готовьтесь, скоро будет и официальный анонс.\n\n*4.* ОDS растет и развивается не только в Москве - есть и локальные тусовки!\n- В Минске прошла первая тренировка (и планируется следующая), в эту субботу пройдет первый Дата Завтрак, а в августе состоится митап под эгидой ODS. Вся движуха в <#C4TJ1PLKV|_meetings_minsk>.\n- В Киеве и Львове регулярно проходят встречи Ukrainian Data Science Club по вторникам и субботам. Часть людей занимается time series, часть CV – мультиклассовая классификация, knowledge distillation и оптимизация сеточек. Больше информации в <#C0VL96SJ2|_meetings_ukraine> и тут: <https:\/\/www.facebook.com\/groups\/1081438678569043\/>\n- Продолжаются тренировки в Одессе. Ближайшая состоится вечером в среду 9 августа в ОНУ им. Мечникова. Подробности в <#C0VL96SJ2|_meetings_ukraine>.\n- Мероприятия активно проходят и в других городах России. Например, в следующую среду в Новосибирске пройдет митап в 2ГИС <#C0KUUAAJZ|_meetings_siberia>. А ближе к осени тренировки и DS митапы вновь запустятся по всему СНГ.\n- Возвращаясь к тренировкам <#C1CEM43TJ|mltrainings_live> - ближайшая встреча в Москве пройдет уже в эту субботу 29 июля: <https:\/\/events.yandex.ru\/events\/mltr\/29-jul-2017\/>\n\n*5.* Осенью мы планируем запустить новый сезон сериала про машинное обучение на хабре. Хотелось бы в течение осени публиковать как минимум по одной статье в неделю в блоге на хабре <https:\/\/habrahabr.ru\/company\/ods\/>. \nСейчас на нас подписано 1600 человек, и эта цифра растет ежедневно. В среднем в сутки наши статьи набирают по 5000 просмотров, а в дни публикаций и до 10 000. За весенний сезон мы смогли подняться на третье место в рейтинге компаний (и за лето упасть до 15-20). В новом сезоне хотелось бы добиться еще лучших результатов, но без вас, естественно, мы не справимся. \nЕсли вы очень хотите написать пост про ваш опыт, про какую-либо статью, которую вы недавно прочитали, про какую-то базовую модель, да вообще про что угодно – пишите <@U06J1LG1M>. У нас есть табличка куда можно вписать свое имя и тему поста <https:\/\/goo.gl\/2KHD9B>, дату публикации можно вводить с погрешностью 1-2 недели.\n\n*P.S.* Сухая статистика: 5413 участников, 1.25М сообщений от участников (новая аналитика не включает сообщения от ботов, и такие технические вещи как добавленные файлы)",
                "author_name": "Alex Natekin",
                "author_link": "https:\/\/opendatascience.slack.com\/team\/natekin",
                "author_icon": "https:\/\/avatars.slack-edge.com\/2016-09-15\/80071260369_86dbff4518f09c916e0a_48.jpg",
                "mrkdwn_in": [
                    "text"
                ],
                "id": 1,
                "footer": "Posted in #_general"
            }
        ]
    },
    {
        "type": "message",
        "text": "&gt; ОDS растет и развивается не только в Москве - есть и локальные тусовки!\n&gt; - В Минске прошла ...\n&gt; - В Киеве и Львове ...\n&gt; - Продолжаются тренировки в Одессе ...\n&gt; - Мероприятия активно проходят и в других городах России.",
        "user": "U47EZESD8",
        "ts": "1501165525.754386",
        "team": "T040HKJE3",
        "user_team": "T040HKJE3",
        "source_team": "T040HKJE3",
        "user_profile": {
            "avatar_hash": "32f8ee79d56e",
            "image_72": "https:\/\/avatars.slack-edge.com\/2017-03-16\/154456742608_32f8ee79d56e4ff029df_72.jpg",
            "first_name": "Nickolai",
            "real_name": "Nickolai Kruglikov",
            "display_name": "untech",
            "team": "T040HKJE3",
            "name": "untech",
            "is_restricted": false,
            "is_ultra_restricted": false
        },
        "edited": {
            "user": "U47EZESD8",
            "ts": "1501165551.000000"
        }
    },
    {
        "type": "message",
        "text": ":wat:",
        "user": "U04725QK7",
        "ts": "1501165583.790622",
        "team": "T040HKJE3",
        "user_team": "T040HKJE3",
        "source_team": "T040HKJE3",
        "user_profile": {
            "avatar_hash": "6c5a2eb7d11b",
            "image_72": "https:\/\/avatars.slack-edge.com\/2017-04-06\/165204167890_6c5a2eb7d11ba847fb69_72.png",
            "first_name": "Gleb",
            "real_name": "Gleb Filatov",
            "display_name": "gleb_filatov",
            "team": "T040HKJE3",
            "name": "gleb_filatov",
            "is_restricted": false,
            "is_ultra_restricted": false
        }
    },
    {
        "type": "message",
        "text": "<http:\/\/yann.lecun.com\/ex\/images\/allyourbayes.jpg>",
        "user": "U040HKJE7",
        "ts": "1501166524.397035",
        "team": "T040HKJE3",
        "user_team": "T040HKJE3",
        "source_team": "T040HKJE3",
        "user_profile": {
            "avatar_hash": "910ffe66f361",
            "image_72": "https:\/\/avatars.slack-edge.com\/2017-12-25\/291044574499_910ffe66f3612ed5c505_72.jpg",
            "first_name": "Alex",
            "real_name": "Alex Natekin",
            "display_name": "natekin",
            "team": "T040HKJE3",
            "name": "natekin",
            "is_restricted": false,
            "is_ultra_restricted": false
        },
        "attachments": [
            {
                "fallback": "640x480px image",
                "image_url": "http:\/\/yann.lecun.com\/ex\/images\/allyourbayes.jpg",
                "image_width": 640,
                "image_height": 480,
                "image_bytes": 55355,
                "from_url": "http:\/\/yann.lecun.com\/ex\/images\/allyourbayes.jpg",
                "id": 1
            }
        ],
        "reactions": [
            {
                "name": "slow",
                "users": [
                    "U04725QK7"
                ],
                "count": 1
            },
            {
                "name": "meh",
                "users": [
                    "U36Q9NJMD"
                ],
                "count": 1
            },
            {
                "name": "bajan",
                "users": [
                    "U04ELQZAU"
                ],
                "count": 1
            },
            {
                "name": "heavy_multiplication_x",
                "users": [
                    "U04ELQZAU"
                ],
                "count": 1
            },
            {
                "name": "infinity",
                "users": [
                    "U04ELQZAU"
                ],
                "count": 1
            }
        ]
    },
    {
        "type": "message",
        "text": "Это же PAC-Learning?",
        "user": "U04725QK7",
        "ts": "1501166559.419983",
        "team": "T040HKJE3",
        "user_team": "T040HKJE3",
        "source_team": "T040HKJE3",
        "user_profile": {
            "avatar_hash": "6c5a2eb7d11b",
            "image_72": "https:\/\/avatars.slack-edge.com\/2017-04-06\/165204167890_6c5a2eb7d11ba847fb69_72.png",
            "first_name": "Gleb",
            "real_name": "Gleb Filatov",
            "display_name": "gleb_filatov",
            "team": "T040HKJE3",
            "name": "gleb_filatov",
            "is_restricted": false,
            "is_ultra_restricted": false
        },
        "reactions": [
            {
                "name": "heavy_minus_sign",
                "users": [
                    "U04ELQZAU"
                ],
                "count": 1
            }
        ]
    }
]