[
    {
        "type": "message",
        "text": "<http:\/\/dashboard.securingdemocracy.org>",
        "user": "U48A8L25N",
        "ts": "1501763808.571705",
        "team": "T040HKJE3",
        "user_team": "T040HKJE3",
        "source_team": "T040HKJE3",
        "user_profile": {
            "avatar_hash": "80555db3b28e",
            "image_72": "https:\/\/avatars.slack-edge.com\/2017-06-24\/202244047937_80555db3b28e977842fb_72.png",
            "first_name": "Данияр",
            "real_name": "Данияр Елеусизов",
            "display_name": "daniyarel",
            "team": "T040HKJE3",
            "name": "daniyarel",
            "is_restricted": false,
            "is_ultra_restricted": false
        },
        "attachments": [
            {
                "service_name": "Hamilton 68",
                "title": "Hamilton 68: Tracking Putin's Propaganda Push... To America",
                "title_link": "http:\/\/dashboard.securingdemocracy.org",
                "text": "Tracking Russian twitter account to better understand their influence in US politics.",
                "fallback": "Hamilton 68: Hamilton 68: Tracking Putin's Propaganda Push... To America",
                "from_url": "http:\/\/dashboard.securingdemocracy.org",
                "service_icon": "http:\/\/dashboard.securingdemocracy.org\/favicon.ico?v=2",
                "id": 1
            }
        ]
    },
    {
        "type": "message",
        "text": "&gt;A DASHBOARD TRACKING RUSSIAN PROPAGANDA ON TWITTER",
        "user": "U48A8L25N",
        "ts": "1501763904.607216",
        "team": "T040HKJE3",
        "user_team": "T040HKJE3",
        "source_team": "T040HKJE3",
        "user_profile": {
            "avatar_hash": "80555db3b28e",
            "image_72": "https:\/\/avatars.slack-edge.com\/2017-06-24\/202244047937_80555db3b28e977842fb_72.png",
            "first_name": "Данияр",
            "real_name": "Данияр Елеусизов",
            "display_name": "daniyarel",
            "team": "T040HKJE3",
            "name": "daniyarel",
            "is_restricted": false,
            "is_ultra_restricted": false
        },
        "edited": {
            "user": "U48A8L25N",
            "ts": "1501763914.000000"
        }
    },
    {
        "type": "message",
        "text": "<http:\/\/pix.my\/o\/Tuv1aG?1501763980>",
        "user": "U48A8L25N",
        "ts": "1501764005.645522",
        "team": "T040HKJE3",
        "user_team": "T040HKJE3",
        "source_team": "T040HKJE3",
        "user_profile": {
            "avatar_hash": "80555db3b28e",
            "image_72": "https:\/\/avatars.slack-edge.com\/2017-06-24\/202244047937_80555db3b28e977842fb_72.png",
            "first_name": "Данияр",
            "real_name": "Данияр Елеусизов",
            "display_name": "daniyarel",
            "team": "T040HKJE3",
            "name": "daniyarel",
            "is_restricted": false,
            "is_ultra_restricted": false
        },
        "attachments": [
            {
                "fallback": "1077x292px image",
                "image_url": "http:\/\/pix.my\/o\/Tuv1aG?1501763980",
                "image_width": 1077,
                "image_height": 292,
                "image_bytes": 801809,
                "from_url": "http:\/\/pix.my\/o\/Tuv1aG?1501763980",
                "id": 1
            }
        ]
    },
    {
        "type": "message",
        "text": "<https:\/\/www.znak.com\/2017-08-03\/polpred_yufo_schitaet_naznachenie_plemyannicy_rogozina_glavoy_nacparka_sochi_necelesoobraznym>",
        "user": "U48A8L25N",
        "ts": "1501786043.347107",
        "team": "T040HKJE3",
        "user_team": "T040HKJE3",
        "source_team": "T040HKJE3",
        "user_profile": {
            "avatar_hash": "80555db3b28e",
            "image_72": "https:\/\/avatars.slack-edge.com\/2017-06-24\/202244047937_80555db3b28e977842fb_72.png",
            "first_name": "Данияр",
            "real_name": "Данияр Елеусизов",
            "display_name": "daniyarel",
            "team": "T040HKJE3",
            "name": "daniyarel",
            "is_restricted": false,
            "is_ultra_restricted": false
        }
    },
    {
        "type": "message",
        "text": "&gt;Полпред ЮФО считает назначение «племянницы Рогозина» главой нацпарка Сочи нецелесообразным\n&gt;За последние пять лет сменила более пяти мест работы, с периодичностью от полутора лет до одного месяца. В течение последних полутора лет допустила около сорока административных правонарушений",
        "user": "U48A8L25N",
        "ts": "1501786070.362617",
        "team": "T040HKJE3",
        "user_team": "T040HKJE3",
        "source_team": "T040HKJE3",
        "user_profile": {
            "avatar_hash": "80555db3b28e",
            "image_72": "https:\/\/avatars.slack-edge.com\/2017-06-24\/202244047937_80555db3b28e977842fb_72.png",
            "first_name": "Данияр",
            "real_name": "Данияр Елеусизов",
            "display_name": "daniyarel",
            "team": "T040HKJE3",
            "name": "daniyarel",
            "is_restricted": false,
            "is_ultra_restricted": false
        }
    },
    {
        "type": "message",
        "text": "40 Карл! за полторагода!",
        "user": "U48A8L25N",
        "ts": "1501786081.368435",
        "team": "T040HKJE3",
        "user_team": "T040HKJE3",
        "source_team": "T040HKJE3",
        "user_profile": {
            "avatar_hash": "80555db3b28e",
            "image_72": "https:\/\/avatars.slack-edge.com\/2017-06-24\/202244047937_80555db3b28e977842fb_72.png",
            "first_name": "Данияр",
            "real_name": "Данияр Елеусизов",
            "display_name": "daniyarel",
            "team": "T040HKJE3",
            "name": "daniyarel",
            "is_restricted": false,
            "is_ultra_restricted": false
        },
        "edited": {
            "user": "U48A8L25N",
            "ts": "1501786096.000000"
        }
    },
    {
        "type": "message",
        "text": "Занятно, что человека называют не по имени фамилии",
        "user": "U04725QK7",
        "ts": "1501786215.441857",
        "team": "T040HKJE3",
        "user_team": "T040HKJE3",
        "source_team": "T040HKJE3",
        "user_profile": {
            "avatar_hash": "6c5a2eb7d11b",
            "image_72": "https:\/\/avatars.slack-edge.com\/2017-04-06\/165204167890_6c5a2eb7d11ba847fb69_72.png",
            "first_name": "Gleb",
            "real_name": "Gleb Filatov",
            "display_name": "gleb_filatov",
            "team": "T040HKJE3",
            "name": "gleb_filatov",
            "is_restricted": false,
            "is_ultra_restricted": false
        }
    },
    {
        "type": "message",
        "text": "А \"племянница рогозина\"",
        "user": "U04725QK7",
        "ts": "1501786222.446323",
        "team": "T040HKJE3",
        "user_team": "T040HKJE3",
        "source_team": "T040HKJE3",
        "user_profile": {
            "avatar_hash": "6c5a2eb7d11b",
            "image_72": "https:\/\/avatars.slack-edge.com\/2017-04-06\/165204167890_6c5a2eb7d11ba847fb69_72.png",
            "first_name": "Gleb",
            "real_name": "Gleb Filatov",
            "display_name": "gleb_filatov",
            "team": "T040HKJE3",
            "name": "gleb_filatov",
            "is_restricted": false,
            "is_ultra_restricted": false
        }
    }
]