[
    {
        "client_msg_id": "23a069e2-bbc4-4390-aa03-a3f549ed882f",
        "type": "message",
        "text": "<https:\/\/www.youtube.com\/watch?v=zO4tcfaHPdo>",
        "user": "U27HU84H4",
        "ts": "1564597786.022800",
        "team": "T040HKJE3",
        "user_team": "T040HKJE3",
        "source_team": "T040HKJE3",
        "user_profile": {
            "avatar_hash": "7ec7ef7154ba",
            "image_72": "https:\/\/avatars.slack-edge.com\/2018-04-26\/354236189286_7ec7ef7154baf1b9e9b5_72.jpg",
            "first_name": "Leonid",
            "real_name": "Leonid Sinev",
            "display_name": "leonid",
            "team": "T040HKJE3",
            "name": "leonid",
            "is_restricted": false,
            "is_ultra_restricted": false
        },
        "attachments": [
            {
                "service_name": "YouTube",
                "service_url": "https:\/\/www.youtube.com\/",
                "title": "Массовые задержания в Москве. Акции Яндекса упали из-за нового законопроекта. Дмитрий Потапенко",
                "title_link": "https:\/\/www.youtube.com\/watch?v=zO4tcfaHPdo",
                "author_name": "Дмитрий ПОТАПЕНКО",
                "author_link": "https:\/\/www.youtube.com\/channel\/UC54SBo5_usXGEoybX1ZVETQ",
                "thumb_url": "https:\/\/i.ytimg.com\/vi\/zO4tcfaHPdo\/hqdefault.jpg",
                "thumb_width": 480,
                "thumb_height": 360,
                "fallback": "YouTube Video: Массовые задержания в Москве. Акции Яндекса упали из-за нового законопроекта. Дмитрий Потапенко",
                "video_html": "<iframe width=\"400\" height=\"225\" src=\"https:\/\/www.youtube.com\/embed\/zO4tcfaHPdo?feature=oembed&autoplay=1&iv_load_policy=3\" frameborder=\"0\" allow=\"accelerometer; autoplay; encrypted-media; gyroscope; picture-in-picture\" allowfullscreen><\/iframe>",
                "video_html_width": 400,
                "video_html_height": 225,
                "from_url": "https:\/\/www.youtube.com\/watch?v=zO4tcfaHPdo",
                "service_icon": "https:\/\/a.slack-edge.com\/2089\/img\/unfurl_icons\/youtube.png",
                "id": 1,
                "original_url": "https:\/\/www.youtube.com\/watch?v=zO4tcfaHPdo"
            }
        ],
        "reactions": [
            {
                "name": "yeah-sure",
                "users": [
                    "U48A8L25N"
                ],
                "count": 1
            }
        ]
    }
]