[
    {
        "client_msg_id": "328aedab-86e0-4aaa-a5f0-8b8fd772f096",
        "type": "message",
        "text": "<https:\/\/www.youtube.com\/watch?v=lsxldz87HXI>",
        "user": "U27HU84H4",
        "ts": "1587663358.082700",
        "team": "T040HKJE3",
        "user_team": "T040HKJE3",
        "source_team": "T040HKJE3",
        "user_profile": {
            "avatar_hash": "7ec7ef7154ba",
            "image_72": "https:\/\/avatars.slack-edge.com\/2018-04-26\/354236189286_7ec7ef7154baf1b9e9b5_72.jpg",
            "first_name": "Leonid",
            "real_name": "Leonid Sinev",
            "display_name": "leonid",
            "team": "T040HKJE3",
            "name": "leonid",
            "is_restricted": false,
            "is_ultra_restricted": false
        },
        "attachments": [
            {
                "service_name": "YouTube",
                "service_url": "https:\/\/www.youtube.com\/",
                "title": "«Потапенко будит!», Интерактив, Штрафы за нарушение режима самоизоляции",
                "title_link": "https:\/\/www.youtube.com\/watch?v=lsxldz87HXI",
                "author_name": "Серебряный Дождь",
                "author_link": "https:\/\/www.youtube.com\/user\/wwwsilverru",
                "thumb_url": "https:\/\/i.ytimg.com\/vi\/lsxldz87HXI\/hqdefault.jpg",
                "thumb_width": 480,
                "thumb_height": 360,
                "fallback": "YouTube Video: «Потапенко будит!», Интерактив, Штрафы за нарушение режима самоизоляции",
                "video_html": "<iframe width=\"400\" height=\"225\" src=\"https:\/\/www.youtube.com\/embed\/lsxldz87HXI?feature=oembed&autoplay=1&iv_load_policy=3\" frameborder=\"0\" allow=\"accelerometer; autoplay; encrypted-media; gyroscope; picture-in-picture\" allowfullscreen><\/iframe>",
                "video_html_width": 400,
                "video_html_height": 225,
                "from_url": "https:\/\/www.youtube.com\/watch?v=lsxldz87HXI",
                "service_icon": "https:\/\/a.slack-edge.com\/80588\/img\/unfurl_icons\/youtube.png",
                "id": 1,
                "original_url": "https:\/\/www.youtube.com\/watch?v=lsxldz87HXI"
            }
        ],
        "blocks": [
            {
                "type": "rich_text",
                "block_id": "pbt",
                "elements": [
                    {
                        "type": "rich_text_section",
                        "elements": [
                            {
                                "type": "link",
                                "url": "https:\/\/www.youtube.com\/watch?v=lsxldz87HXI"
                            }
                        ]
                    }
                ]
            }
        ]
    },
    {
        "client_msg_id": "4e944e5f-0dae-40b0-a094-def0ff2043cd",
        "type": "message",
        "text": "<https:\/\/www.youtube.com\/watch?v=__TGy7BCaQM>",
        "user": "U27HU84H4",
        "ts": "1587670094.083000",
        "team": "T040HKJE3",
        "user_team": "T040HKJE3",
        "source_team": "T040HKJE3",
        "user_profile": {
            "avatar_hash": "7ec7ef7154ba",
            "image_72": "https:\/\/avatars.slack-edge.com\/2018-04-26\/354236189286_7ec7ef7154baf1b9e9b5_72.jpg",
            "first_name": "Leonid",
            "real_name": "Leonid Sinev",
            "display_name": "leonid",
            "team": "T040HKJE3",
            "name": "leonid",
            "is_restricted": false,
            "is_ultra_restricted": false
        },
        "attachments": [
            {
                "service_name": "YouTube",
                "service_url": "https:\/\/www.youtube.com\/",
                "title": "Ленин и три признака революционной ситуации: эфир на радио Комсомольская правда.- 22 апреля 2020",
                "title_link": "https:\/\/www.youtube.com\/watch?v=__TGy7BCaQM",
                "author_name": "Екатерина Шульман",
                "author_link": "https:\/\/www.youtube.com\/channel\/UCL1rJ0ROIw9V1qFeIN0ZTZQ",
                "thumb_url": "https:\/\/i.ytimg.com\/vi\/__TGy7BCaQM\/hqdefault.jpg",
                "thumb_width": 480,
                "thumb_height": 360,
                "fallback": "YouTube Video: Ленин и три признака революционной ситуации: эфир на радио Комсомольская правда.- 22 апреля 2020",
                "video_html": "<iframe width=\"400\" height=\"225\" src=\"https:\/\/www.youtube.com\/embed\/__TGy7BCaQM?feature=oembed&autoplay=1&iv_load_policy=3\" frameborder=\"0\" allow=\"accelerometer; autoplay; encrypted-media; gyroscope; picture-in-picture\" allowfullscreen><\/iframe>",
                "video_html_width": 400,
                "video_html_height": 225,
                "from_url": "https:\/\/www.youtube.com\/watch?v=__TGy7BCaQM",
                "service_icon": "https:\/\/a.slack-edge.com\/80588\/img\/unfurl_icons\/youtube.png",
                "id": 1,
                "original_url": "https:\/\/www.youtube.com\/watch?v=__TGy7BCaQM"
            }
        ],
        "blocks": [
            {
                "type": "rich_text",
                "block_id": "oAapq",
                "elements": [
                    {
                        "type": "rich_text_section",
                        "elements": [
                            {
                                "type": "link",
                                "url": "https:\/\/www.youtube.com\/watch?v=__TGy7BCaQM"
                            }
                        ]
                    }
                ]
            }
        ]
    }
]